jax_shape_tracker-0.1.1.dist-info/licenses/LICENSE
shape_tracker/__init__.py
shape_tracker/__main__.py
shape_tracker/_shape_bug_tracker.py
jax_shape_tracker-0.1.1.dist-info/METADATA
jax_shape_tracker-0.1.1.dist-info/WHEEL
jax_shape_tracker-0.1.1.dist-info/entry_points.txt
jax_shape_tracker-0.1.1.dist-info/top_level.txt
jax_shape_tracker-0.1.1.dist-info/RECORD
