Metadata-Version: 2.4
Name: jax-shape-tracker
Version: 0.1.1
Summary: Pinpoint JAX shape errors at the exact user code line
Author: Kris
License-Expression: MIT
Project-URL: Homepage, https://github.com/KrisTHL181/jax-shape-tracker
Project-URL: Issues, https://github.com/KrisTHL181/jax-shape-tracker/issues
Keywords: jax,debugging,shape,xla,ml
Classifier: Development Status :: 3 - Alpha
Classifier: Intended Audience :: Developers
Classifier: Programming Language :: Python :: 3
Classifier: Programming Language :: Python :: 3.9
Classifier: Programming Language :: Python :: 3.10
Classifier: Programming Language :: Python :: 3.11
Classifier: Programming Language :: Python :: 3.12
Classifier: Topic :: Software Development :: Debuggers
Classifier: Topic :: Scientific/Engineering :: Artificial Intelligence
Requires-Python: >=3.9
License-File: LICENSE
Requires-Dist: jax
Provides-Extra: color
Requires-Dist: colorama; extra == "color"
Dynamic: license-file
